msimg/__init__.py
msimg/callbacks.py
msimg/config.py
msimg/constants.py
msimg/exceptions.py
msimg/generator.py
msimg/image_uploader.py
msimg/strategies.py
msimg/version.py
msimg/wechat_uploader.py
msimg-0.0.4.dist-info/LICENSE
msimg-0.0.4.dist-info/METADATA
msimg-0.0.4.dist-info/WHEEL
msimg-0.0.4.dist-info/RECORD
