Metadata-Version: 2.3
Name: msimg
Version: 0.0.4
Summary: 🎨 一个优雅的魔塔社区文生图API调用库，支持多模型、多API、容错重试、内置8种图床等高级特性
License: MIT
Keywords: modelscope,text-to-image,ai,image-generation,flux,qwen,image-uploader
Author: Xiaoqiang
Author-email: xiaoqiangclub@hotmail.com
Requires-Python: >=3.8.1
Classifier: Development Status :: 4 - Beta
Classifier: Intended Audience :: Developers
Classifier: License :: OSI Approved :: MIT License
Classifier: Programming Language :: Python :: 3
Classifier: Programming Language :: Python :: 3.9
Classifier: Programming Language :: Python :: 3.10
Classifier: Programming Language :: Python :: 3.11
Classifier: Programming Language :: Python :: 3.12
Classifier: Programming Language :: Python :: 3.13
Classifier: Programming Language :: Python :: 3.8
Classifier: Topic :: Scientific/Engineering :: Artificial Intelligence
Classifier: Topic :: Software Development :: Libraries :: Python Modules
Provides-Extra: aliyun
Provides-Extra: all
Provides-Extra: qiniu
Provides-Extra: upyun
Requires-Dist: Pillow (>=10.0.0)
Requires-Dist: oss2 (>=2.18.0) ; extra == "aliyun" or extra == "all"
Requires-Dist: qiniu (>=7.12.0) ; extra == "qiniu" or extra == "all"
Requires-Dist: requests (>=2.31.0)
Requires-Dist: upyun (>=2.5.0) ; extra == "upyun" or extra == "all"
Project-URL: Bug Tracker, https://github.com/xiaoqiangclub/msimg/issues
Project-URL: Homepage, https://github.com/xiaoqiangclub/msimg
Project-URL: Repository, https://github.com/xiaoqiangclub/msimg
